cmhlims/__init__.py
cmhlims/config.ini
cmhlims/connectToLIMS.py
cmhlims/getAnalysis.py
cmhlims/getAnalysisFiles.py
cmhlims/getSampleNames.py
cmhlims/setConfig.py
tests/__init__.py
tests/test.py
tests/test_connectToLIMS.py
tests/test_getAnalysis.py
tests/test_getAnalysisFiles.py
tests/test_getSampleNames.py
cmh_lims_py-1.0.17.dist-info/LICENSE.txt
cmh_lims_py-1.0.17.dist-info/METADATA
cmh_lims_py-1.0.17.dist-info/WHEEL
cmh_lims_py-1.0.17.dist-info/top_level.txt
cmh_lims_py-1.0.17.dist-info/RECORD
